<?xml version="1.0" encoding="UTF-8"?>
<tasks>
	<task start="1">
		<label><![CDATA[If category_id;]]></label>
		<id><![CDATA[d45ddc36_0323629c_369]]></id>
		<type><![CDATA[d45ddc36]]></type>
		<tag><![CDATA[if]]></tag>
		<offset_left>100</offset_left>
		<offset_top>50</offset_top>
		<width>70</width>
		<height>65</height>
		<properties>
			<group>
				<join><![CDATA[and]]></join>
				<item>
					<first>
						<value><![CDATA[$category_id]]></value>
						<type><![CDATA[variable]]></type>
					</first>
					<operator><![CDATA[==]]></operator>
					<second>
						<value><![CDATA[true]]></value>
						<type></type>
					</second>
				</item>
			</group>
			<exits>
				<true>
					<color><![CDATA[#51D87A]]></color>
					<label><![CDATA[True]]></label>
				</true>
				<false>
					<color><![CDATA[#FF4D4D]]></color>
					<label><![CDATA[False]]></label>
				</false>
			</exits>
		</properties>
		<exits>
			<true>
				<task_id><![CDATA[b70dfcdb_6c7f232a_241]]></task_id>
				<label><![CDATA[True]]></label>
				<type><![CDATA[Straight]]></type>
				<overlay><![CDATA[Forward Arrow]]></overlay>
				<color><![CDATA[#51D87A]]></color>
			</true>
			<false>
				<task_id><![CDATA[b70dfcdb_a853de3f_553]]></task_id>
				<label><![CDATA[False]]></label>
				<type><![CDATA[Straight]]></type>
				<overlay><![CDATA[Forward Arrow]]></overlay>
				<color><![CDATA[#FF4D4D]]></color>
			</false>
		</exits>
	</task>
	<task>
		<label><![CDATA[Init $data]]></label>
		<id><![CDATA[b70dfcdb_6c7f232a_241]]></id>
		<type><![CDATA[b70dfcdb]]></type>
		<tag><![CDATA[setarray]]></tag>
		<offset_left>100</offset_left>
		<offset_top>190</offset_top>
		<width>70</width>
		<height>65</height>
		<properties>
			<result_var_name><![CDATA[data]]></result_var_name>
			<result_var_assignment></result_var_assignment>
			<items>
				<key><![CDATA[conditions]]></key>
				<key_type><![CDATA[string]]></key_type>
				<items>
					<key><![CDATA[category_id]]></key>
					<key_type><![CDATA[string]]></key_type>
					<value><![CDATA[$category_id]]></value>
					<value_type><![CDATA[variable]]></value_type>
				</items>
			</items>
			<exits>
				<default_exit>
					<color><![CDATA[#426efa]]></color>
				</default_exit>
			</exits>
		</properties>
		<exits>
			<default_exit>
				<task_id><![CDATA[1e5acc1c_bfba9d91_508]]></task_id>
				<label></label>
				<type><![CDATA[Straight]]></type>
				<overlay><![CDATA[Forward Arrow]]></overlay>
				<color><![CDATA[#426efa]]></color>
			</default_exit>
		</exits>
	</task>
	<task>
		<label><![CDATA[BL: sample/stockmanager.ProductService.getAll]]></label>
		<id><![CDATA[1e5acc1c_bfba9d91_508]]></id>
		<type><![CDATA[1e5acc1c]]></type>
		<tag><![CDATA[callbusinesslogic]]></tag>
		<offset_left>100</offset_left>
		<offset_top>330</offset_top>
		<width>70</width>
		<height>75</height>
		<properties>
			<result_var_name><![CDATA[result]]></result_var_name>
			<result_var_assignment></result_var_assignment>
			<method_obj><![CDATA[$EVC->getBroker("soa")]]></method_obj>
			<module_id><![CDATA[sample/stockmanager]]></module_id>
			<module_id_type><![CDATA[string]]></module_id_type>
			<service_id><![CDATA[ProductService.getAll]]></service_id>
			<service_id_type><![CDATA[string]]></service_id_type>
			<parameters><![CDATA[$data]]></parameters>
			<parameters_type><![CDATA[variable]]></parameters_type>
			<options>
				<key><![CDATA[no_cache]]></key>
				<key_type><![CDATA[string]]></key_type>
				<value><![CDATA[$no_cache]]></value>
				<value_type><![CDATA[variable]]></value_type>
			</options>
			<options_type><![CDATA[array]]></options_type>
			<exits>
				<default_exit>
					<color><![CDATA[#426efa]]></color>
				</default_exit>
			</exits>
		</properties>
		<exits>
			<default_exit>
				<task_id><![CDATA[b70dfcdb_a853de3f_553]]></task_id>
				<label></label>
				<type><![CDATA[Straight]]></type>
				<overlay><![CDATA[Forward Arrow]]></overlay>
				<color><![CDATA[#426efa]]></color>
			</default_exit>
		</exits>
	</task>
	<task>
		<label><![CDATA[Init $options]]></label>
		<id><![CDATA[b70dfcdb_a853de3f_553]]></id>
		<type><![CDATA[b70dfcdb]]></type>
		<tag><![CDATA[setarray]]></tag>
		<offset_left>100</offset_left>
		<offset_top>470</offset_top>
		<width>70</width>
		<height>65</height>
		<properties>
			<result_var_name><![CDATA[options]]></result_var_name>
			<result_var_assignment></result_var_assignment>
			<items></items>
			<exits>
				<default_exit>
					<color><![CDATA[#426efa]]></color>
				</default_exit>
			</exits>
		</properties>
		<exits>
			<default_exit>
				<task_id><![CDATA[d45ddc36_793ed275_945]]></task_id>
				<label></label>
				<type><![CDATA[Straight]]></type>
				<overlay><![CDATA[Forward Arrow]]></overlay>
				<color><![CDATA[#426efa]]></color>
			</default_exit>
		</exits>
	</task>
	<task>
		<label><![CDATA[If result;]]></label>
		<id><![CDATA[d45ddc36_793ed275_945]]></id>
		<type><![CDATA[d45ddc36]]></type>
		<tag><![CDATA[if]]></tag>
		<offset_left>100</offset_left>
		<offset_top>610</offset_top>
		<width>70</width>
		<height>65</height>
		<properties>
			<group>
				<join><![CDATA[and]]></join>
				<item>
					<first>
						<value><![CDATA[$result]]></value>
						<type><![CDATA[variable]]></type>
					</first>
					<operator><![CDATA[==]]></operator>
					<second>
						<value><![CDATA[true]]></value>
						<type></type>
					</second>
				</item>
			</group>
			<exits>
				<true>
					<color><![CDATA[#51D87A]]></color>
					<label><![CDATA[True]]></label>
				</true>
				<false>
					<color><![CDATA[#FF4D4D]]></color>
					<label><![CDATA[False]]></label>
				</false>
			</exits>
		</properties>
		<exits>
			<true>
				<task_id><![CDATA[cdcf04c1_2f2d56d8_176]]></task_id>
				<label><![CDATA[True]]></label>
				<type><![CDATA[Straight]]></type>
				<overlay><![CDATA[Forward Arrow]]></overlay>
				<color><![CDATA[#51D87A]]></color>
			</true>
			<false>
				<task_id><![CDATA[d1e9c332_ac84ce96_343]]></task_id>
				<label><![CDATA[False]]></label>
				<type><![CDATA[Straight]]></type>
				<overlay><![CDATA[Forward Arrow]]></overlay>
				<color><![CDATA[#FF4D4D]]></color>
			</false>
		</exits>
	</task>
	<task>
		<label><![CDATA[Loop]]></label>
		<id><![CDATA[cdcf04c1_2f2d56d8_176]]></id>
		<type><![CDATA[cdcf04c1]]></type>
		<tag><![CDATA[loop]]></tag>
		<offset_left>100</offset_left>
		<offset_top>750</offset_top>
		<width>70</width>
		<height>65</height>
		<properties>
			<init>
				<name><![CDATA[$i]]></name>
				<value>0</value>
				<type></type>
			</init>
			<init>
				<name><![CDATA[$t]]></name>
				<value><![CDATA[count($result)]]></value>
				<type><![CDATA[function]]></type>
			</init>
			<cond>
				<group>
					<join><![CDATA[and]]></join>
					<item>
						<operator><![CDATA[<]]></operator>
						<first>
							<value><![CDATA[$i]]></value>
							<type><![CDATA[variable]]></type>
						</first>
						<second>
							<value><![CDATA[$t]]></value>
							<type><![CDATA[variable]]></type>
						</second>
					</item>
				</group>
			</cond>
			<inc>
				<name><![CDATA[$i]]></name>
				<inc_or_dec><![CDATA[inc]]></inc_or_dec>
			</inc>
			<execute_first_iteration>0</execute_first_iteration>
			<exits>
				<start_exit>
					<color><![CDATA[#31498f]]></color>
					<label><![CDATA[Start loop]]></label>
				</start_exit>
				<default_exit>
					<color><![CDATA[#2C2D34]]></color>
					<label><![CDATA[End loop]]></label>
				</default_exit>
			</exits>
		</properties>
		<exits>
			<default_exit>
				<task_id><![CDATA[d1e9c332_ac84ce96_343]]></task_id>
				<label><![CDATA[End loop]]></label>
				<type><![CDATA[Straight]]></type>
				<overlay><![CDATA[Forward Arrow]]></overlay>
				<color><![CDATA[#2C2D34]]></color>
			</default_exit>
			<start_exit>
				<task_id><![CDATA[6d1db313_fab35830_293]]></task_id>
				<label><![CDATA[Start loop]]></label>
				<type><![CDATA[Straight]]></type>
				<overlay><![CDATA[Forward Arrow]]></overlay>
				<color><![CDATA[#31498f]]></color>
			</start_exit>
		</exits>
	</task>
	<task>
		<label><![CDATA[Define var item]]></label>
		<id><![CDATA[6d1db313_fab35830_293]]></id>
		<type><![CDATA[6d1db313]]></type>
		<tag><![CDATA[setvar]]></tag>
		<offset_left>160</offset_left>
		<offset_top>890</offset_top>
		<width>70</width>
		<height>65</height>
		<properties>
			<result_var_name><![CDATA[item]]></result_var_name>
			<result_var_assignment></result_var_assignment>
			<value><![CDATA[$result[$i]]]></value>
			<type></type>
			<exits>
				<default_exit>
					<color><![CDATA[#426efa]]></color>
				</default_exit>
			</exits>
		</properties>
		<exits>
			<default_exit>
				<task_id><![CDATA[6d1db313_4df132c4_924]]></task_id>
				<label></label>
				<type><![CDATA[Straight]]></type>
				<overlay><![CDATA[Forward Arrow]]></overlay>
				<color><![CDATA[#426efa]]></color>
			</default_exit>
		</exits>
	</task>
	<task>
		<label><![CDATA[Define var key]]></label>
		<id><![CDATA[6d1db313_4df132c4_924]]></id>
		<type><![CDATA[6d1db313]]></type>
		<tag><![CDATA[setvar]]></tag>
		<offset_left>160</offset_left>
		<offset_top>1030</offset_top>
		<width>70</width>
		<height>65</height>
		<properties>
			<result_var_name><![CDATA[key]]></result_var_name>
			<result_var_assignment></result_var_assignment>
			<value><![CDATA[$item["product_id"]]]></value>
			<type></type>
			<exits>
				<default_exit>
					<color><![CDATA[#426efa]]></color>
				</default_exit>
			</exits>
		</properties>
		<exits>
			<default_exit>
				<task_id><![CDATA[6d1db313_ccee7935_58]]></task_id>
				<label></label>
				<type><![CDATA[Straight]]></type>
				<overlay><![CDATA[Forward Arrow]]></overlay>
				<color><![CDATA[#426efa]]></color>
			</default_exit>
		</exits>
	</task>
	<task>
		<label><![CDATA[Define var value]]></label>
		<id><![CDATA[6d1db313_ccee7935_58]]></id>
		<type><![CDATA[6d1db313]]></type>
		<tag><![CDATA[setvar]]></tag>
		<offset_left>160</offset_left>
		<offset_top>1170</offset_top>
		<width>70</width>
		<height>65</height>
		<properties>
			<result_var_name><![CDATA[value]]></result_var_name>
			<result_var_assignment></result_var_assignment>
			<value><![CDATA[$item["name"]]]></value>
			<type></type>
			<exits>
				<default_exit>
					<color><![CDATA[#426efa]]></color>
				</default_exit>
			</exits>
		</properties>
		<exits>
			<default_exit>
				<task_id><![CDATA[6d1db313_097035e6_935]]></task_id>
				<label></label>
				<type><![CDATA[Straight]]></type>
				<overlay><![CDATA[Forward Arrow]]></overlay>
				<color><![CDATA[#426efa]]></color>
			</default_exit>
		</exits>
	</task>
	<task>
		<label><![CDATA[Define var options[$key]]]></label>
		<id><![CDATA[6d1db313_097035e6_935]]></id>
		<type><![CDATA[6d1db313]]></type>
		<tag><![CDATA[setvar]]></tag>
		<offset_left>160</offset_left>
		<offset_top>1310</offset_top>
		<width>70</width>
		<height>65</height>
		<properties>
			<result_var_name><![CDATA[options[$key]]]></result_var_name>
			<result_var_assignment></result_var_assignment>
			<value><![CDATA[$value]]></value>
			<type><![CDATA[variable]]></type>
			<exits>
				<default_exit>
					<color><![CDATA[#426efa]]></color>
				</default_exit>
			</exits>
		</properties>
	</task>
	<task>
		<label><![CDATA[Return options]]></label>
		<id><![CDATA[d1e9c332_ac84ce96_343]]></id>
		<type><![CDATA[d1e9c332]]></type>
		<tag><![CDATA[return]]></tag>
		<offset_left>100</offset_left>
		<offset_top>890</offset_top>
		<width>70</width>
		<height>65</height>
		<properties>
			<value><![CDATA[$options]]></value>
			<type><![CDATA[variable]]></type>
			<exits></exits>
		</properties>
	</task>
</tasks>